openapi_trimmer/__init__.py
openapi_trimmer/main.py
openapi_trimmer-0.1.4.dist-info/LICENSE
openapi_trimmer-0.1.4.dist-info/METADATA
openapi_trimmer-0.1.4.dist-info/WHEEL
openapi_trimmer-0.1.4.dist-info/entry_points.txt
openapi_trimmer-0.1.4.dist-info/top_level.txt
openapi_trimmer-0.1.4.dist-info/RECORD
