Metadata-Version: 2.1
Name: openapi-trimmer
Version: 0.1.4
Summary: Tool to trim OpenAPI YAML file to include only desired paths and components.
Home-page: https://github.com/idachev/openapi-trimmer
Author: Ivan Dachev
Author-email: i_dachev@yahoo.co.uk
License: MIT
Classifier: Programming Language :: Python :: 3
Classifier: License :: OSI Approved :: MIT License
Classifier: Operating System :: OS Independent
Requires-Python: >=3.10
License-File: LICENSE
Requires-Dist: setuptools
Requires-Dist: pyyaml >=6
